<?xml version="1.0" encoding="UTF-8"?>
<UIStates>
    <Binder Show="Yes">
        <ShowCollections>No</ShowCollections>
        <SelectedCollection>0</SelectedCollection>
        <SubdocumentCounts>No</SubdocumentCounts>
        <ExpandedItems>
            <ItemID>BD9E202A-A848-4C04-B1DF-342B13D88B58</ItemID>
            <ItemID>219A8713-C6F1-4F23-8B6B-CAC82530C3DF</ItemID>
            <ItemID>96E223E1-3449-48EB-81A0-17CE9D4C8D70</ItemID>
            <ItemID>3AF0EEC7-75B5-4C79-A777-74CAB0A444B9</ItemID>
            <ItemID>F573BF27-9E87-4C46-95F3-2DC49E23FA72</ItemID>
            <ItemID>17555F18-8B15-46C1-BDE5-4E81B51A397C</ItemID>
            <ItemID>0F95C87D-98B1-4887-B2DA-9CCE6CEB7024</ItemID>
            <ItemID>19B822B5-FDF7-42A6-ACC1-397278C2280F</ItemID>
            <ItemID>DD1C2275-23D4-4881-B5E7-893566AEFC2D</ItemID>
            <ItemID>99E727F0-2E9E-4C1D-BC7D-0138033D4556</ItemID>
            <ItemID>4568AB40-7042-4F69-9BC3-C92260C1B335</ItemID>
            <ItemID>F79FB0F3-C574-41C5-9EF6-A61DAE9267F1</ItemID>
            <ItemID>DEEE3D34-F0A1-480A-960B-91FBD17DDEA4</ItemID>
            <ItemID>0A7A44F8-7BA4-48EF-965D-A0698D614BC5</ItemID>
        </ExpandedItems>
        <Selection>
            <ItemID>74882803-D20C-43FB-9451-67A2DA3DF0E3</ItemID>
        </Selection>
        <SearchResultsSort Titles="Ascending" Dates="Ascending">None</SearchResultsSort>
    </Binder>
    <Inspector Show="No" View="MetaData">
        <ShowProjectBookmarks>No</ShowProjectBookmarks>
        <Collapse>Notes</Collapse>
        <FootnoteNumbers Prompt="No">No</FootnoteNumbers>
    </Inspector>
    <Split>None</Split>
    <BinderAffects>Current</BinderAffects>
    <Labels>
        <Binder FullWidth="No">No</Binder>
        <Icons>No</Icons>
        <IndexCards>No</IndexCards>
        <OutlinerRows>No</OutlinerRows>
        <ScriveningsTitles>No</ScriveningsTitles>
    </Labels>
    <Corkboards>
        <LabelIndicators>Yes</LabelIndicators>
        <Stamps>No</Stamps>
        <Keywords>No</Keywords>
        <Numbers Restart="No">No</Numbers>
        <SnapToGrid>No</SnapToGrid>
        <BlankCardsAGhosts>No</BlankCardsAGhosts>
    </Corkboards>
    <Text>
        <ShowFormatBar>Yes</ShowFormatBar>
        <UseVerticalLayout>No</UseVerticalLayout>
        <ShowScriveningsTitles>No</ShowScriveningsTitles>
        <ShowInvisibles>No</ShowInvisibles>
        <RevisionMode>0</RevisionMode>
        <TextChecking>
            <Spelling>No</Spelling>
            <Grammar>No</Grammar>
            <SmartQuotes>Yes</SmartQuotes>
            <SmartDashes>Yes</SmartDashes>
        </TextChecking>
    </Text>
    <ProjectKeywords>
        <ExpandedItems>
            <ItemID>4</ItemID>
            <ItemID>2</ItemID>
            <ItemID>5</ItemID>
            <ItemID>13</ItemID>
            <ItemID>17</ItemID>
        </ExpandedItems>
    </ProjectKeywords>
    <FullScreen>
        <ShowRuler>No</ShowRuler>
        <PageLayout Facing="No">No</PageLayout>
        <TypewriterScrolling>Yes</TypewriterScrolling>
    </FullScreen>
    <Editors Primary="Editor2">
        <Editor1>
            <View>
                <ShowHeader>Yes</ShowHeader>
                <ShowFooter>Yes</ShowFooter>
                <GroupsViewMode>Corkboard</GroupsViewMode>
                <CurrentViewMode>Single</CurrentViewMode>
                <SelectionAffects>None</SelectionAffects>
                <NavigationHistory CurrentIndex="-1"></NavigationHistory>
            </View>
            <Text>
                <ShowRuler>No</ShowRuler>
                <PageLayout Facing="No">No</PageLayout>
                <TypewriterScrolling>No</TypewriterScrolling>
                <LineNumbers Interval="1">No</LineNumbers>
                <Selection>0,0</Selection>
            </Text>
            <Outliner>
                <Columns>
                    <ColID>title</ColID>
                    <ColID>label</ColID>
                    <ColID>status</ColID>
                    <ColID>sectionType</ColID>
                </Columns>
                <TitlesOnly>No</TitlesOnly>
                <HideIcons>No</HideIcons>
                <ShowNumbers>No</ShowNumbers>
                <KeywordsAsChips>Yes</KeywordsAsChips>
                <FixedRowHeights>No</FixedRowHeights>
            </Outliner>
            <Corkboard>
                <CardsAcross>-1</CardsAcross>
                <KeywordChips>5</KeywordChips>
                <SizeCardsToFit>Yes</SizeCardsToFit>
                <CardHeightRatio>0.6666</CardHeightRatio>
                <SectionsArrangement>Wrap</SectionsArrangement>
                <LabelThreadsUseColumns>No</LabelThreadsUseColumns>
            </Corkboard>
            <Copyholder PreferredOrientation="Vertical" VerticalPos="Right" HorizontalPos="Bottom">
                <Text>
                    <ShowRuler>No</ShowRuler>
                    <PageLayout Facing="No">No</PageLayout>
                    <TypewriterScrolling>No</TypewriterScrolling>
                    <LineNumbers Interval="1">No</LineNumbers>
                </Text>
            </Copyholder>
        </Editor1>
        <Editor2>
            <View>
                <ShowHeader>Yes</ShowHeader>
                <ShowFooter>Yes</ShowFooter>
                <GroupsViewMode>Corkboard</GroupsViewMode>
                <CurrentViewMode>Corkboard</CurrentViewMode>
                <SelectionAffects>None</SelectionAffects>
                <Content>
                    <ItemID>74882803-D20C-43FB-9451-67A2DA3DF0E3</ItemID>
                </Content>
                <NavigationHistory CurrentIndex="91">
                    <HistoryItem Type="BinderItems" ViewMode="Single">E40A8246-BFC3-43A9-912B-D701ECD8CC2B</HistoryItem>
                    <HistoryItem Type="BinderItems" ViewMode="Single">2B124788-65AB-4954-8A5C-A571E5DEB473</HistoryItem>
                    <HistoryItem Type="BinderItems" ViewMode="Single">E40A8246-BFC3-43A9-912B-D701ECD8CC2B</HistoryItem>
                    <HistoryItem Type="BinderItems" ViewMode="Single">2B124788-65AB-4954-8A5C-A571E5DEB473</HistoryItem>
                    <HistoryItem Type="BinderItems" ViewMode="Single">E40A8246-BFC3-43A9-912B-D701ECD8CC2B</HistoryItem>
                    <HistoryItem Type="BinderItems" ViewMode="Single">2B124788-65AB-4954-8A5C-A571E5DEB473</HistoryItem>
                    <HistoryItem Type="BinderItems" ViewMode="Single">E40A8246-BFC3-43A9-912B-D701ECD8CC2B</HistoryItem>
                    <HistoryItem Type="BinderItems" ViewMode="Single">B0279873-B7E1-43F0-84F5-9C8D02B582B3</HistoryItem>
                    <HistoryItem Type="BinderItems" ViewMode="Single">2B124788-65AB-4954-8A5C-A571E5DEB473</HistoryItem>
                    <HistoryItem Type="BinderItems" ViewMode="Single">E40A8246-BFC3-43A9-912B-D701ECD8CC2B</HistoryItem>
                    <HistoryItem Type="BinderItems" ViewMode="Single">B0279873-B7E1-43F0-84F5-9C8D02B582B3</HistoryItem>
                    <HistoryItem Type="BinderItems" ViewMode="Single">19B822B5-FDF7-42A6-ACC1-397278C2280F</HistoryItem>
                    <HistoryItem Type="BinderItems" ViewMode="Single">A1416F0E-CB12-4944-BAE8-F8F7149CD3D9</HistoryItem>
                    <HistoryItem Type="BinderItems" ViewMode="Single">C91381F1-AA35-4056-AF95-315E4D1F4061</HistoryItem>
                    <HistoryItem Type="BinderItems" ViewMode="Single">A86AC0E1-90E6-41B6-A474-A28B0CED258E</HistoryItem>
                    <HistoryItem Type="BinderItems" ViewMode="Single">C91381F1-AA35-4056-AF95-315E4D1F4061</HistoryItem>
                    <HistoryItem Type="BinderItems" ViewMode="Single">5C8274F5-503F-44BC-AFFA-F71F2FF7C5EA</HistoryItem>
                    <HistoryItem Type="BinderItems" ViewMode="Single">C91381F1-AA35-4056-AF95-315E4D1F4061</HistoryItem>
                    <HistoryItem Type="BinderItems" ViewMode="Single">17555F18-8B15-46C1-BDE5-4E81B51A397C</HistoryItem>
                    <HistoryItem Type="BinderItems" ViewMode="Single">19B822B5-FDF7-42A6-ACC1-397278C2280F</HistoryItem>
                    <HistoryItem Type="BinderItems" ViewMode="Single">50856214-6622-41AD-9FA0-DADB6FD109D6</HistoryItem>
                    <HistoryItem Type="BinderItems" ViewMode="Single">6F5FF54A-C2E4-44CC-A126-C6FBC64EDDE7</HistoryItem>
                    <HistoryItem Type="BinderItems" ViewMode="Single">75B7DDD2-FA65-44ED-A34D-B41692CB3CC0</HistoryItem>
                    <HistoryItem Type="BinderItems" ViewMode="Single">71C13EB7-4B3F-4F86-99B3-D86D022EF8CF</HistoryItem>
                    <HistoryItem Type="BinderItems" ViewMode="Single">960DC116-862A-4BFC-B0C6-0E307AB4C4A7</HistoryItem>
                    <HistoryItem Type="BinderItems" ViewMode="Single">99E727F0-2E9E-4C1D-BC7D-0138033D4556</HistoryItem>
                    <HistoryItem Type="BinderItems" ViewMode="Single">17555F18-8B15-46C1-BDE5-4E81B51A397C</HistoryItem>
                    <HistoryItem Type="BinderItems" ViewMode="Single">99E727F0-2E9E-4C1D-BC7D-0138033D4556</HistoryItem>
                    <HistoryItem Type="BinderItems" ViewMode="Single">17555F18-8B15-46C1-BDE5-4E81B51A397C</HistoryItem>
                    <HistoryItem Type="BinderItems" ViewMode="Single">99E727F0-2E9E-4C1D-BC7D-0138033D4556</HistoryItem>
                    <HistoryItem Type="BinderItems" ViewMode="Single">17555F18-8B15-46C1-BDE5-4E81B51A397C</HistoryItem>
                    <HistoryItem Type="BinderItems" ViewMode="Single">99E727F0-2E9E-4C1D-BC7D-0138033D4556</HistoryItem>
                    <HistoryItem Type="BinderItems" ViewMode="Single">D25092C9-02F0-4BAB-AD9A-78BEA3491773</HistoryItem>
                    <HistoryItem Type="BinderItems" ViewMode="Single">17555F18-8B15-46C1-BDE5-4E81B51A397C</HistoryItem>
                    <HistoryItem Type="BinderItems" ViewMode="Single">BDA0A47E-0276-4B66-AC4B-958323884B52</HistoryItem>
                    <HistoryItem Type="BinderItems" ViewMode="Single">17555F18-8B15-46C1-BDE5-4E81B51A397C</HistoryItem>
                    <HistoryItem Type="BinderItems" ViewMode="Single">99E727F0-2E9E-4C1D-BC7D-0138033D4556</HistoryItem>
                    <HistoryItem Type="BinderItems" ViewMode="Single">9DBB6049-FF98-42FA-B129-139D7D10542F</HistoryItem>
                    <HistoryItem Type="BinderItems" ViewMode="Single">B0279873-B7E1-43F0-84F5-9C8D02B582B3</HistoryItem>
                    <HistoryItem Type="BinderItems" ViewMode="Single">E40A8246-BFC3-43A9-912B-D701ECD8CC2B</HistoryItem>
                    <HistoryItem Type="BinderItems" ViewMode="Single">2B124788-65AB-4954-8A5C-A571E5DEB473</HistoryItem>
                    <HistoryItem Type="BinderItems" ViewMode="Single">6FABBE4F-A34D-4171-9F86-ED6E380B3265</HistoryItem>
                    <HistoryItem Type="BinderItems" ViewMode="Single">9DBB6049-FF98-42FA-B129-139D7D10542F</HistoryItem>
                    <HistoryItem Type="BinderItems" ViewMode="Single">DD1C2275-23D4-4881-B5E7-893566AEFC2D</HistoryItem>
                    <HistoryItem Type="BinderItems" ViewMode="Single">3DA91C22-82A0-4181-AE36-C902D3AC2C05</HistoryItem>
                    <HistoryItem Type="BinderItems" ViewMode="Single">C91381F1-AA35-4056-AF95-315E4D1F4061</HistoryItem>
                    <HistoryItem Type="BinderItems" ViewMode="Single">5C8274F5-503F-44BC-AFFA-F71F2FF7C5EA</HistoryItem>
                    <HistoryItem Type="BinderItems" ViewMode="Single">C91381F1-AA35-4056-AF95-315E4D1F4061</HistoryItem>
                    <HistoryItem Type="BinderItems" ViewMode="Single">2477BF28-8059-4D3B-A536-8143E75CA719</HistoryItem>
                    <HistoryItem Type="BinderItems" ViewMode="Single">E2714989-B6F8-44D2-96E6-92F4865E193C</HistoryItem>
                    <HistoryItem Type="BinderItems" ViewMode="Single">2FFCDF7C-5FB2-4AF7-827C-D512C2F260BC</HistoryItem>
                    <HistoryItem Type="BinderItems" ViewMode="Single">342FDF9D-1529-4238-B456-21068A18FF7B</HistoryItem>
                    <HistoryItem Type="BinderItems" ViewMode="Single">2FFCDF7C-5FB2-4AF7-827C-D512C2F260BC</HistoryItem>
                    <HistoryItem Type="BinderItems" ViewMode="Single">EAA12A56-30FC-4C0D-830A-96282420858A</HistoryItem>
                    <HistoryItem Type="BinderItems" ViewMode="Single">97ED0614-A23C-4886-ACE7-BE856E4FC323</HistoryItem>
                    <HistoryItem Type="BinderItems" ViewMode="Corkboard">47805A6B-C856-48E6-9415-EF6105B745BB,69C0BF89-6A59-4CBB-A8FE-18028BB45B59</HistoryItem>
                    <HistoryItem Type="BinderItems" ViewMode="Single">97ED0614-A23C-4886-ACE7-BE856E4FC323</HistoryItem>
                    <HistoryItem Type="BinderItems" ViewMode="Single">EAA12A56-30FC-4C0D-830A-96282420858A</HistoryItem>
                    <HistoryItem Type="BinderItems" ViewMode="Single">B0249D2F-3CC6-4132-9895-4334653A3933</HistoryItem>
                    <HistoryItem Type="BinderItems" ViewMode="Single">3AC20CBA-EF0F-41A5-A08C-2EBC16F24A81</HistoryItem>
                    <HistoryItem Type="BinderItems" ViewMode="Single">17555F18-8B15-46C1-BDE5-4E81B51A397C</HistoryItem>
                    <HistoryItem Type="BinderItems" ViewMode="Corkboard">F573BF27-9E87-4C46-95F3-2DC49E23FA72</HistoryItem>
                    <HistoryItem Type="BinderItems" ViewMode="Single">3AC20CBA-EF0F-41A5-A08C-2EBC16F24A81</HistoryItem>
                    <HistoryItem Type="BinderItems" ViewMode="Single">0A7A44F8-7BA4-48EF-965D-A0698D614BC5</HistoryItem>
                    <HistoryItem Type="BinderItems" ViewMode="Single">32A423B4-3F7C-4004-A478-EBA0E8F368BA</HistoryItem>
                    <HistoryItem Type="BinderItems" ViewMode="Corkboard">32A423B4-3F7C-4004-A478-EBA0E8F368BA,B246839C-19D4-4CFB-B3D1-64F776620A88,0E09D559-06DA-4B20-B10F-2474783EF8D6,936C3F40-F5F9-4153-911A-21A9A5B9DC1F</HistoryItem>
                    <HistoryItem Type="BinderItems" ViewMode="Single">0A7A44F8-7BA4-48EF-965D-A0698D614BC5</HistoryItem>
                    <HistoryItem Type="BinderItems" ViewMode="Corkboard">74882803-D20C-43FB-9451-67A2DA3DF0E3</HistoryItem>
                    <HistoryItem Type="BinderItems" ViewMode="Single">219A8713-C6F1-4F23-8B6B-CAC82530C3DF</HistoryItem>
                    <HistoryItem Type="BinderItems" ViewMode="Single">617D1B8A-6F06-4AA5-908B-07AB2C46349C</HistoryItem>
                    <HistoryItem Type="BinderItems" ViewMode="Single">2F5DC88D-FC57-48E2-B9AC-00FB19912292</HistoryItem>
                    <HistoryItem Type="BinderItems" ViewMode="Single">ADD02D86-A84E-4483-A076-55567E85C4D4</HistoryItem>
                    <HistoryItem Type="BinderItems" ViewMode="Single">F79FB0F3-C574-41C5-9EF6-A61DAE9267F1</HistoryItem>
                    <HistoryItem Type="BinderItems" ViewMode="Single">3AC20CBA-EF0F-41A5-A08C-2EBC16F24A81</HistoryItem>
                    <HistoryItem Type="BinderItems" ViewMode="Single">EAA12A56-30FC-4C0D-830A-96282420858A</HistoryItem>
                    <HistoryItem Type="BinderItems" ViewMode="Single">C5EB0C6E-C10B-421A-9F14-B1E7BA1269D8</HistoryItem>
                    <HistoryItem Type="BinderItems" ViewMode="Single">97ED0614-A23C-4886-ACE7-BE856E4FC323</HistoryItem>
                    <HistoryItem Type="BinderItems" ViewMode="Single">C5EB0C6E-C10B-421A-9F14-B1E7BA1269D8</HistoryItem>
                    <HistoryItem Type="BinderItems" ViewMode="Single">EAA12A56-30FC-4C0D-830A-96282420858A</HistoryItem>
                    <HistoryItem Type="BinderItems" ViewMode="Single">C5EB0C6E-C10B-421A-9F14-B1E7BA1269D8</HistoryItem>
                    <HistoryItem Type="BinderItems" ViewMode="Single">EAA12A56-30FC-4C0D-830A-96282420858A</HistoryItem>
                    <HistoryItem Type="BinderItems" ViewMode="Single">189A9259-835B-4F3B-84B8-E56DE1E24231</HistoryItem>
                    <HistoryItem Type="BinderItems" ViewMode="Corkboard">189A9259-835B-4F3B-84B8-E56DE1E24231,6D219B8D-6DF7-4841-A44A-3C6DDB099CDE,1A9555C1-494B-44A8-8DDA-D6A584B5A662</HistoryItem>
                    <HistoryItem Type="BinderItems" ViewMode="Single">97ED0614-A23C-4886-ACE7-BE856E4FC323</HistoryItem>
                    <HistoryItem Type="BinderItems" ViewMode="Single">C5EB0C6E-C10B-421A-9F14-B1E7BA1269D8</HistoryItem>
                    <HistoryItem Type="BinderItems" ViewMode="Single">EAA12A56-30FC-4C0D-830A-96282420858A</HistoryItem>
                    <HistoryItem Type="BinderItems" ViewMode="Single">3AC20CBA-EF0F-41A5-A08C-2EBC16F24A81</HistoryItem>
                    <HistoryItem Type="BinderItems" ViewMode="Single">F79FB0F3-C574-41C5-9EF6-A61DAE9267F1</HistoryItem>
                    <HistoryItem Type="BinderItems" ViewMode="Single">DEEE3D34-F0A1-480A-960B-91FBD17DDEA4</HistoryItem>
                    <HistoryItem Type="BinderItems" ViewMode="Single">936C3F40-F5F9-4153-911A-21A9A5B9DC1F</HistoryItem>
                    <HistoryItem Type="BinderItems" ViewMode="Single">12E31EBC-077B-4AB2-AB2A-0B25ABC098B8</HistoryItem>
                    <HistoryItem Type="BinderItems" ViewMode="Corkboard">74882803-D20C-43FB-9451-67A2DA3DF0E3</HistoryItem>
                </NavigationHistory>
            </View>
            <Text>
                <ShowRuler>No</ShowRuler>
                <PageLayout Facing="No">No</PageLayout>
                <TypewriterScrolling>No</TypewriterScrolling>
                <LineNumbers Interval="1">No</LineNumbers>
                <Selection>122,0</Selection>
            </Text>
            <Outliner>
                <Columns>
                    <ColID>title</ColID>
                    <ColID>label</ColID>
                    <ColID>status</ColID>
                    <ColID>sectionType</ColID>
                </Columns>
                <TitlesOnly>No</TitlesOnly>
                <HideIcons>No</HideIcons>
                <ShowNumbers>No</ShowNumbers>
                <KeywordsAsChips>Yes</KeywordsAsChips>
                <FixedRowHeights>No</FixedRowHeights>
            </Outliner>
            <Corkboard>
                <CardsAcross>-1</CardsAcross>
                <KeywordChips>5</KeywordChips>
                <SizeCardsToFit>Yes</SizeCardsToFit>
                <CardHeightRatio>0.6666</CardHeightRatio>
                <SectionsArrangement>Wrap</SectionsArrangement>
                <LabelThreadsUseColumns>No</LabelThreadsUseColumns>
            </Corkboard>
            <Copyholder PreferredOrientation="Vertical" VerticalPos="Right" HorizontalPos="Bottom">
                <Text>
                    <ShowRuler>No</ShowRuler>
                    <PageLayout Facing="No">No</PageLayout>
                    <TypewriterScrolling>No</TypewriterScrolling>
                    <LineNumbers Interval="1">No</LineNumbers>
                </Text>
            </Copyholder>
        </Editor2>
    </Editors>
</UIStates>